{ "height":10,
 "layers":[
        {
         "draworder":"topdown",
         "name":"Object Layer 1",
         "objects":[
                {
                 "height":68,
                 "id":1,
                 "name":"platform",
                 "rotation":0,
                 "type":"platform",
                 "visible":true,
                 "width":269,
                 "x":1.5,
                 "y":143
                }, 
                {
                 "height":68,
                 "id":2,
                 "name":"platform",
                 "rotation":0,
                 "type":"platform",
                 "visible":true,
                 "width":197,
                 "x":356.5,
                 "y":140
                }, 
                {
                 "height":68,
                 "id":3,
                 "name":"platform",
                 "rotation":0,
                 "type":"platform",
                 "visible":true,
                 "width":415,
                 "x":637.5,
                 "y":349
                }, 
                {
                 "height":68,
                 "id":4,
                 "name":"platform",
                 "rotation":0,
                 "type":"platform",
                 "visible":true,
                 "width":199,
                 "x":353.5,
                 "y":352
                }, 
                {
                 "height":68,
                 "id":5,
                 "name":"platform",
                 "rotation":0,
                 "type":"platform",
                 "visible":true,
                 "width":131,
                 "x":146.5,
                 "y":351
                }, 
                {
                 "height":68,
                 "id":6,
                 "name":"platform",
                 "rotation":0,
                 "type":"platform",
                 "visible":true,
                 "width":206,
                 "x":845.5,
                 "y":632
                }, 
                {
                 "height":68,
                 "id":7,
                 "name":"platform",
                 "rotation":0,
                 "type":"platform",
                 "visible":true,
                 "width":60,
                 "x":705.5,
                 "y":631
                }, 
                {
                 "height":68,
                 "id":8,
                 "name":"platform",
                 "rotation":0,
                 "type":"platform",
                 "visible":true,
                 "width":63,
                 "x":494.5,
                 "y":632
                }, 
                {
                 "height":68,
                 "id":9,
                 "name":"platform",
                 "rotation":0,
                 "type":"platform",
                 "visible":true,
                 "width":62,
                 "x":284.5,
                 "y":633
                }, 
                {
                 "height":68,
                 "id":10,
                 "name":"platform",
                 "rotation":0,
                 "type":"platform",
                 "visible":true,
                 "width":136,
                 "x":-0.5,
                 "y":633
                }, 
                {
                 "height":68,
                 "id":11,
                 "name":"platform",
                 "rotation":0,
                 "type":"platform",
                 "visible":true,
                 "width":125,
                 "x":708.5,
                 "y":140
                }, 
                {
                 "height":701,
                 "id":12,
                 "name":"platform",
                 "rotation":0,
                 "type":"platform",
                 "visible":true,
                 "width":0,
                 "x":-1.5,
                 "y":0
                }, 
                {
                 "height":701,
                 "id":13,
                 "name":"platform",
                 "rotation":0,
                 "type":"platform",
                 "visible":true,
                 "width":0,
                 "x":1052,
                 "y":-1.5
                }, 
                {
                 "height":1,
                 "id":14,
                 "name":"platform",
                 "rotation":0,
                 "type":"platform",
                 "visible":true,
                 "width":1055,
                 "x":-1,
                 "y":-0.5
                }, 
                {
                 "height":114,
                 "id":15,
                 "name":"",
                 "rotation":0,
                 "type":"door",
                 "visible":true,
                 "width":65.3333,
                 "x":983.33335,
                 "y":517
                }, 
                {
                 "height":31,
                 "id":16,
                 "name":"water",
                 "rotation":0,
                 "type":"water",
                 "visible":true,
                 "width":136,
                 "x":144,
                 "y":666.5
                }, 
                {
                 "height":31,
                 "id":17,
                 "name":"water",
                 "rotation":0,
                 "type":"water",
                 "visible":true,
                 "width":136,
                 "x":353,
                 "y":667.5
                }, 
                {
                 "height":31,
                 "id":18,
                 "name":"water",
                 "rotation":0,
                 "type":"water",
                 "visible":true,
                 "width":136,
                 "x":562,
                 "y":669.5
                }, 
                {
                 "height":31,
                 "id":19,
                 "name":"water",
                 "rotation":0,
                 "type":"water",
                 "visible":true,
                 "width":66,
                 "x":771,
                 "y":666.5
                }, 
                {
                 "height":31,
                 "id":20,
                 "name":"water",
                 "rotation":0,
                 "type":"water",
                 "visible":true,
                 "width":136,
                 "x":562,
                 "y":171.5
                }, 
                {
                 "height":31,
                 "id":21,
                 "name":"water",
                 "rotation":0,
                 "type":"water",
                 "visible":true,
                 "width":68,
                 "x":280,
                 "y":175.5
                }, 
                {
                 "height":31,
                 "id":22,
                 "name":"water",
                 "rotation":0,
                 "type":"water",
                 "visible":true,
                 "width":68,
                 "x":284,
                 "y":387.5
                }, 
                {
                 "height":31,
                 "id":23,
                 "name":"water",
                 "rotation":0,
                 "type":"water",
                 "visible":true,
                 "width":68,
                 "x":561,
                 "y":387.5
                }, 
                {
                 "height":45.3333,
                 "id":24,
                 "name":"",
                 "rotation":0,
                 "type":"coin",
                 "visible":true,
                 "width":45.3333,
                 "x":293.33335,
                 "y":569.33335
                }, 
                {
                 "height":45.3333,
                 "id":25,
                 "name":"",
                 "rotation":0,
                 "type":"coin",
                 "visible":true,
                 "width":45.3333,
                 "x":501.33335,
                 "y":574.33335
                }, 
                {
                 "height":45.3333,
                 "id":26,
                 "name":"",
                 "rotation":0,
                 "type":"coin",
                 "visible":true,
                 "width":45.3333,
                 "x":713.33335,
                 "y":584.33335
                }, 
                {
                 "height":45.3333,
                 "id":27,
                 "name":"",
                 "rotation":0,
                 "type":"coin",
                 "visible":true,
                 "width":45.3333,
                 "x":991.33335,
                 "y":89.33335
                }, 
                {
                 "height":45.3333,
                 "id":28,
                 "name":"",
                 "rotation":0,
                 "type":"coin",
                 "visible":true,
                 "width":45.3333,
                 "x":433.33335,
                 "y":223.33335
                }],
         "opacity":1,
         "type":"objectgroup",
         "visible":true,
         "x":0,
         "y":0
        }, 
        {
         "data":[0, 0, 0, 0, 0, 0, 0, 0, 0, 0, 0, 0, 0, 0, 0, 0, 0, 0, 0, 0, 0, 0, 0, 0, 0, 0, 0, 0, 0, 0, 101, 101, 101, 101, 151, 101, 101, 101, 151, 151, 101, 101, 0, 0, 0, 0, 0, 0, 0, 0, 0, 0, 0, 0, 0, 0, 0, 0, 0, 0, 0, 0, 0, 0, 0, 0, 0, 0, 0, 0, 0, 0, 0, 0, 0, 0, 0, 101, 101, 151, 101, 101, 101, 151, 101, 101, 101, 101, 101, 101, 0, 0, 0, 0, 0, 0, 0, 0, 0, 0, 0, 0, 0, 0, 0, 0, 0, 0, 0, 0, 0, 0, 0, 0, 0, 0, 0, 0, 0, 46, 0, 0, 0, 0, 0, 0, 0, 0, 0, 0, 0, 0, 0, 0, 58, 101, 101, 151, 151, 101, 151, 151, 101, 151, 151, 101, 151, 101, 101, 101],
         "height":10,
         "name":"Tile Layer 1",
         "opacity":1,
         "type":"tilelayer",
         "visible":true,
         "width":15,
         "x":0,
         "y":0
        }],
 "nextobjectid":29,
 "orientation":"orthogonal",
 "renderorder":"right-down",
 "tiledversion":"1.0.1",
 "tileheight":70,
 "tilesets":[
        {
         "columns":12,
         "firstgid":1,
         "image":"..\/textures\/tiles_spritesheet.png",
         "imageheight":936,
         "imagewidth":914,
         "margin":0,
         "name":"tiles_spritesheet",
         "spacing":2,
         "tilecount":156,
         "tileheight":70,
         "tilewidth":70
        }],
 "tilewidth":70,
 "type":"map",
 "version":1,
 "width":15
}